{"id": "AS13167-MNT", "name": "Merck KGaA AS Maintainer", "admin_id": "KK504-RIPE", "tech_id": "MB826-RIPE", "org_id": "", "created": "1970-01-01", "updated": "2006-11-30", "source": "ripe", "raw": "mntner:         AS13167-MNT\\ndescr:          Merck KGaA AS Maintainer\\nadmin-c:        KK504-RIPE\\ntech-c:         MB826-RIPE\\nupd-to:         isi-ct@merck.de\\nremarks:        MD5 passwords older than November 2011 were removed from this maintainer, see: https://www.ripe.net/removed2011pw\\nmnt-by:         AS13167-MNT\\ncreated:        1970-01-01T00:00:00Z\\nlast-modified:  2006-11-30T14:38:07Z\\nsource:         RIPE"}
{"id": "SHWS-MNT", "name": "", "admin_id": "DUMY-RIPE", "tech_id": "", "org_id": "", "created": "2024-05-16", "updated": "2024-05-16", "source": "ripe", "raw": "mntner:         SHWS-MNT\\nadmin-c:        DUMY-RIPE\\nupd-to:         unread@ripe.net\\nauth:           MD5-PW $1$SaltSalt$DummifiedMD5HashValue.   # Real value hidden for security\\nmnt-by:         SHWS-MNT\\ncreated:        2024-05-16T10:27:10Z\\nlast-modified:  2024-05-16T10:27:10Z\\nsource:         RIPE\\nremarks:        ****************************\\nremarks:        * THIS OBJECT IS MODIFIED\\nremarks:        * Please note that all data that is generally regarded as personal\\nremarks:        * data has been removed from this object.\\nremarks:        * To view the original object, please query the RIPE Database at:\\nremarks:        * http://www.ripe.net/whois\\nremarks:        ****************************\\n"}
{"id": "KRAKENNETWORKISP-MNT", "name": "", "admin_id": "NS9232-RIPE", "tech_id": "", "org_id": "", "created": "2025-04-29", "updated": "2025-04-29", "source": "ripe", "raw": "mntner:         KrakenNetworkISP-MNT\\nadmin-c:        NS9232-RIPE\\nupd-to:         mortalsoft23@gmail.com\\nauth:           SSO\\nmnt-by:         KrakenNetworkISP-MNT\\ncreated:        2025-04-29T17:54:43Z\\nlast-modified:  2025-04-29T17:54:43Z\\nsource:         RIPE"}
{"id": "MNT-CZ-AMCCZ1-1", "name": "Startup maintainer", "admin_id": "LR7818-RIPE", "tech_id": "LR7818-RIPE", "org_id": "", "created": "2019-04-08", "updated": "2019-04-08", "source": "ripe", "raw": "mntner:         mnt-cz-amccz1-1\\ndescr:          Startup maintainer\\nadmin-c:        LR7818-RIPE\\ntech-c:         LR7818-RIPE\\nupd-to:         ruzicka@grapesc.cz\\nauth:           SSO\\nmnt-by:         mnt-cz-amccz1-1\\ncreated:        2019-04-08T07:40:13Z\\nlast-modified:  2019-04-08T07:40:13Z\\nsource:         RIPE"}
{"id": "GENERATED-6RNIHTFWFSO1VZ4UK4SBFXFA706LRJX0-MNT", "name": "Auto-generated maintainer", "admin_id": "AGMT2310-AFRINIC", "tech_id": "", "org_id": "", "created": "", "updated": "", "source": "afrinic", "raw": "mntner:         GENERATED-6RNIHTFWFSO1VZ4UK4SBFXFA706LRJX0-MNT\\ndescr:          Auto-generated maintainer\\nadmin-c:        AGMT2310-AFRINIC\\nauth:           BCRYPT-PW # Filtered\\nmnt-by:         AFRINIC-HM-MNT\\nupd-to:         hostmaster@afrinic.net\\nchanged:        hostmaster@afrinic.net\\nsource:         AFRINIC # Filtered"}
{"id": "MAINT-ID-OMAN", "name": "PT OMAN JAYA PRATAMA\\nJl. DR.Saharjo No. 131\\nManggarai Selatan,Tebet\\nJakarta Selatan 12960", "admin_id": "UZ2-AP", "tech_id": "UZ2-AP", "org_id": "", "created": "", "updated": "2025-02-25", "source": "apnic", "raw": "mntner:         MAINT-ID-OMAN\\ndescr:          PT OMAN JAYA PRATAMA\\ndescr:          Jl. DR.Saharjo No. 131\\ndescr:          Manggarai Selatan,Tebet\\ndescr:          Jakarta Selatan 12960\\nadmin-c:        UZ2-AP\\nupd-to:         ujang.zaenudin@ojphoster.my.id\\nauth:           # Filtered\\nmnt-by:         MAINT-ID-OMAN\\ntech-c:         UZ2-AP\\nlast-modified:  2025-02-25T02:53:20Z\\nsource:         APNIC"}
{"id": "ERX-NET-192-100-97-MNT", "name": "Auto-generated maintainer for ERX", "admin_id": "BNDA7-RIPE\\nHH2039-RIPE\\nMH4573-RIPE", "tech_id": "", "org_id": "", "created": "2004-11-09", "updated": "2005-02-18", "source": "ripe", "raw": "mntner:         ERX-NET-192-100-97-MNT\\ndescr:          Auto-generated maintainer for ERX\\nadmin-c:        BNDA7-RIPE\\nadmin-c:        HH2039-RIPE\\nadmin-c:        MH4573-RIPE\\nupd-to:         er-transfer@ripe.net\\nremarks:        MD5 passwords older than November 2011 were removed from this maintainer, see: https://www.ripe.net/removed2011pw\\nremarks:        \\nremarks:        This maintainer was created for the ERX, and protects\\nremarks:        the inetnum 192.100.97.0 - 192.100.97.255.\\nremarks:        \\nremarks:        For information on how to unlock the network protected\\nremarks:        by this object, please see\\nremarks:        http://www.ripe.net/ripencc/faq/database/erx-faq.html\\nremarks:        \\nmnt-by:         ERX-NET-192-100-97-MNT\\ncreated:        2004-11-09T11:57:59Z\\nlast-modified:  2005-02-18T15:32:17Z\\nsource:         RIPE"}
{"id": "LIR-DK-TIMECOMPUTER-1-MNT", "name": "Startup maintainer", "admin_id": "JS23058-RIPE", "tech_id": "JS23058-RIPE", "org_id": "", "created": "2021-08-02", "updated": "2025-03-12", "source": "ripe", "raw": "mntner:         lir-dk-timecomputer-1-MNT\\ndescr:          Startup maintainer\\nadmin-c:        JS23058-RIPE\\ntech-c:         JS23058-RIPE\\nupd-to:         jan.spure@pro.dk\\nauth:           SSO\\nauth:           SSO\\nauth:           SSO\\nmnt-by:         lir-dk-timecomputer-1-MNT\\ncreated:        2021-08-02T06:52:01Z\\nlast-modified:  2025-03-12T11:47:08Z\\nsource:         RIPE"}
{"id": "NFRICKE-MNT", "name": "", "admin_id": "NF3353-RIPE", "tech_id": "", "org_id": "", "created": "2023-03-12", "updated": "2023-03-12", "source": "ripe", "raw": "mntner:         NFRICKE-MNT\\nadmin-c:        NF3353-RIPE\\nupd-to:         bytehd@peerstudios.net\\nauth:           SSO\\nmnt-by:         NFRICKE-MNT\\ncreated:        2023-03-12T02:07:44Z\\nlast-modified:  2023-03-12T02:07:44Z\\nsource:         RIPE"}
{"id": "GENERATED-W5EEAWCXFGZADOBX9IXQMK46TS1R0R7Y-MNT", "name": "Auto-generated maintainer", "admin_id": "AGMT2310-AFRINIC", "tech_id": "", "org_id": "", "created": "", "updated": "", "source": "afrinic", "raw": "mntner:         GENERATED-W5EEAWCXFGZADOBX9IXQMK46TS1R0R7Y-MNT\\ndescr:          Auto-generated maintainer\\nadmin-c:        AGMT2310-AFRINIC\\nauth:           BCRYPT-PW # Filtered\\nmnt-by:         AFRINIC-HM-MNT\\nupd-to:         ***@afrinic.net\\nchanged:        ***@afrinic.net\\nsource:         AFRINIC\\n"}
{"id": "MNT-PLAYKEY", "name": "", "admin_id": "SAV496-RIPE", "tech_id": "", "org_id": "", "created": "2017-12-18", "updated": "2017-12-28", "source": "ripe", "raw": "mntner:         MNT-PLAYKEY\\nadmin-c:        SAV496-RIPE\\nupd-to:         pi-as@netup.ru\\nauth:           SSO\\nauth:           SSO\\nmnt-by:         MNT-PLAYKEY\\ncreated:        2017-12-18T07:37:07Z\\nlast-modified:  2017-12-28T14:55:37Z\\nsource:         RIPE"}
{"id": "ABIODUN-MNT", "name": "my maintainer", "admin_id": "AA207-AFRINIC", "tech_id": "", "org_id": "", "created": "", "updated": "2018-10-29", "source": "afrinic", "raw": "mntner:         ABIODUN-MNT\\ndescr:          my maintainer\\nadmin-c:        AA207-AFRINIC\\nupd-to:         aadeyeye@coollink.ng\\nauth:           BCRYPT-PW # Filtered\\nmnt-by:         ABIODUN-MNT\\nchanged:        aadeyeye@coollink.ng 20181029\\nsource:         AFRINIC # Filtered"}
{"id": "LIR-DE-AUSECUS-1-MNT", "name": "Startup maintainer", "admin_id": "AGN57-RIPE", "tech_id": "AGN57-RIPE", "org_id": "", "created": "2024-07-08", "updated": "2024-07-08", "source": "ripe", "raw": "mntner:         lir-de-ausecus-1-MNT\\ndescr:          Startup maintainer\\nadmin-c:        AGN57-RIPE\\ntech-c:         AGN57-RIPE\\nupd-to:         noc@ausecus.com\\nauth:           SSO\\nmnt-by:         lir-de-ausecus-1-MNT\\ncreated:        2024-07-08T07:40:19Z\\nlast-modified:  2024-07-08T07:40:19Z\\nsource:         RIPE"}
{"id": "RS-MTSDOO-1-MNT", "name": "Startup maintainer", "admin_id": "BJ2972-RIPE", "tech_id": "BJ2972-RIPE", "org_id": "", "created": "2018-05-01", "updated": "2018-05-01", "source": "ripe", "raw": "mntner:         rs-mtsdoo-1-mnt\\ndescr:          Startup maintainer\\nadmin-c:        BJ2972-RIPE\\ntech-c:         BJ2972-RIPE\\nupd-to:         bratislavj@telekom.rs\\nauth:           SSO\\nmnt-by:         rs-mtsdoo-1-mnt\\ncreated:        2018-05-01T06:07:39Z\\nlast-modified:  2018-05-01T06:07:39Z\\nsource:         RIPE"}
{"id": "ARTEFACT-MNT", "name": "Maintener object for Artefact/Artewan/Arteone\\nReseaux Artewan - Artefact\\nOperateur de reseaux et de services IT", "admin_id": "RE515-RIPE", "tech_id": "RE515-RIPE", "org_id": "ORG-ARTE2-RIPE", "created": "2010-07-01", "updated": "2021-06-24", "source": "ripe", "raw": "mntner:         Artefact-MNT\\ndescr:          Maintener object for Artefact/Artewan/Arteone\\norg:            ORG-ARTE2-RIPE\\ndescr:          Reseaux Artewan - Artefact\\ndescr:          Operateur de reseaux et de services IT\\nremarks:        \\nremarks:        For hacking, spamming or security problems send mail to abuse@artefact.fr\\nremarks:        \\nadmin-c:        RE515-RIPE\\ntech-c:         RE515-RIPE\\nauth:           PGPKEY-ADA445DB\\nauth:           PGPKEY-DFCE53FC\\nauth:           PGPKEY-B8F2CC29\\nauth:           SSO\\nauth:           SSO\\nauth:           SSO\\nmnt-by:         Artefact-MNT\\nremarks:        \\nremarks:        2021-06-24, by Florian Isolet\\nupd-to:         ripe@artewan.net\\ncreated:        2010-07-01T15:23:18Z\\nlast-modified:  2021-06-24T07:17:00Z\\nsource:         RIPE"}
{"id": "LIR-CY-TKBYTECH4-1-MNT", "name": "", "admin_id": "DUMY-RIPE", "tech_id": "", "org_id": "", "created": "2021-08-13", "updated": "2021-08-13", "source": "ripe", "raw": "mntner:         lir-cy-tkbytech4-1-MNT\\nadmin-c:        DUMY-RIPE\\nupd-to:         unread@ripe.net\\nauth:           MD5-PW $1$SaltSalt$DummifiedMD5HashValue.   # Real value hidden for security\\nmnt-by:         lir-cy-tkbytech4-1-MNT\\ncreated:        2021-08-13T08:06:32Z\\nlast-modified:  2021-08-13T08:06:32Z\\nsource:         RIPE\\nremarks:        ****************************\\nremarks:        * THIS OBJECT IS MODIFIED\\nremarks:        * Please note that all data that is generally regarded as personal\\nremarks:        * data has been removed from this object.\\nremarks:        * To view the original object, please query the RIPE Database at:\\nremarks:        * http://www.ripe.net/whois\\nremarks:        ****************************\\n"}
{"id": "MS16812-MNT", "name": "Maintainer", "admin_id": "MS10492-RIPE", "tech_id": "", "org_id": "", "created": "2013-04-10", "updated": "2021-06-04", "source": "ripe", "raw": "mntner:         MS16812-MNT\\ndescr:          Maintainer\\nadmin-c:        MS10492-RIPE\\nupd-to:         martin.straessler@atrete.ch\\nauth:           SSO\\nmnt-by:         MS16812-MNT\\nnotify:         martin.straessler@atrete.ch\\nremarks:        Accepted the RIPE Database Terms and Conditions\\ncreated:        2013-04-10T08:27:54Z\\nlast-modified:  2021-06-04T09:18:54Z\\nsource:         RIPE"}
{"id": "MAINT-IN-VIJAYVISIONNETWORKS", "name": "Vijay Vision", "admin_id": "VD71-AP", "tech_id": "MA630-AP", "org_id": "", "created": "", "updated": "2017-09-30", "source": "apnic", "raw": "mntner:         MAINT-IN-VIJAYVISIONNETWORKS\\ndescr:          Vijay Vision\\ncountry:        IN\\nadmin-c:        VD71-AP\\ntech-c:         MA630-AP\\nupd-to:         vijayvisionnetworks@gmail.com\\nmnt-by:         MAINT-IN-VIJAYVISIONNETWORKS\\nauth:           # Filtered\\nremarks:        send spam and abuse report to vijayvisionnetworks@gmail.com\\nnotify:         vijayvisionnetworks@gmail.com\\nabuse-mailbox:  vijayvisionnetworks@gmail.com\\nreferral-by:    APNIC-HM\\nlast-modified:  2017-09-30T09:03:27Z\\nsource:         APNIC"}
{"id": "MAINT-IN-MEGNET1", "name": "MEGNET", "admin_id": "NM1779-AP", "tech_id": "", "org_id": "", "created": "", "updated": "2021-09-10", "source": "apnic", "raw": "mntner:         MAINT-IN-MEGNET1\\ndescr:          MEGNET\\nadmin-c:        NM1779-AP\\nupd-to:         vinoth@megnet.in\\nmnt-by:         MAINT-IN-MEGNET1\\nauth:           # Filtered\\nlast-modified:  2021-09-10T07:29:34Z\\nsource:         APNIC"}
{"id": "SEVENCS-MNT", "name": "SevenCs Entwicklungsgesellschaft fuer Geo-Informatik mbH\\nRuhrstr. 90, D - 22761 Hamburg, Germany", "admin_id": "GB313-RIPE", "tech_id": "AC55-RIPE", "org_id": "", "created": "1970-01-01", "updated": "2011-03-18", "source": "ripe", "raw": "mntner:         SEVENCS-MNT\\ndescr:          SevenCs Entwicklungsgesellschaft fuer Geo-Informatik mbH\\ndescr:          Ruhrstr. 90, D - 22761 Hamburg, Germany\\nadmin-c:        GB313-RIPE\\ntech-c:         AC55-RIPE\\nupd-to:         noc@sevencs.com\\nmnt-nfy:        noc@sevencs.com\\nremarks:        MD5 passwords older than November 2011 were removed from this maintainer, see: https://www.ripe.net/removed2011pw\\nnotify:         noc@sevencs.com\\nmnt-by:         AMCSNET-MNT\\ncreated:        1970-01-01T00:00:00Z\\nlast-modified:  2011-03-18T11:21:12Z\\nsource:         RIPE"}
{"id": "MCNET", "name": "", "admin_id": "MN11237-RIPE", "tech_id": "", "org_id": "", "created": "2016-07-08", "updated": "2016-07-08", "source": "ripe", "raw": "mntner:         mcnet\\nadmin-c:        MN11237-RIPE\\nupd-to:         endri.meksi@gmail.com\\nauth:           SSO\\nmnt-by:         mcnet\\ncreated:        2016-07-08T08:32:18Z\\nlast-modified:  2016-07-08T08:32:18Z\\nsource:         RIPE"}
{"id": "FR-ACTIA-1-MNT", "name": "Startup maintainer", "admin_id": "AM39160-RIPE", "tech_id": "AM39160-RIPE", "org_id": "", "created": "2016-04-05", "updated": "2016-04-05", "source": "ripe", "raw": "mntner:         fr-actia-1-mnt\\ndescr:          Startup maintainer\\nadmin-c:        AM39160-RIPE\\ntech-c:         AM39160-RIPE\\nupd-to:         ripe@actia.fr\\nauth:           SSO\\nmnt-by:         fr-actia-1-mnt\\ncreated:        2016-04-05T07:23:39Z\\nlast-modified:  2016-04-05T07:23:39Z\\nsource:         RIPE"}
{"id": "GENERATED-3UDWUHGQVHTVXWWJGBN2N4UROZKJYCTW-MNT", "name": "Auto-generated maintainer", "admin_id": "AGMT2310-AFRINIC", "tech_id": "", "org_id": "", "created": "", "updated": "", "source": "afrinic", "raw": "mntner:         GENERATED-3UDWUHGQVHTVXWWJGBN2N4UROZKJYCTW-MNT\\ndescr:          Auto-generated maintainer\\nadmin-c:        AGMT2310-AFRINIC\\nupd-to:         ***@afrinic.net\\nauth:           BCRYPT-PW # Filtered\\nmnt-by:         AFRINIC-HM-MNT\\nchanged:        ***@afrinic.net\\nsource:         AFRINIC\\n"}
{"id": "GENERATED-5UVKTLLV87RL1KELKGQK4PAS1GVLQN02-MNT", "name": "Auto-generated maintainer", "admin_id": "AGMT2310-AFRINIC", "tech_id": "", "org_id": "", "created": "", "updated": "", "source": "afrinic", "raw": "mntner:         GENERATED-5UVKTLLV87RL1KELKGQK4PAS1GVLQN02-MNT\\ndescr:          Auto-generated maintainer\\nadmin-c:        AGMT2310-AFRINIC\\nauth:           BCRYPT-PW # Filtered\\nmnt-by:         AFRINIC-HM-MNT\\nupd-to:         hostmaster@afrinic.net\\nchanged:        hostmaster@afrinic.net\\nsource:         AFRINIC # Filtered"}
{"id": "GENERATED-SHHIZMMOB7U3E6GZAMR0MCO1TGYE4UPU-MNT", "name": "Auto-generated maintainer", "admin_id": "AGMT2310-AFRINIC", "tech_id": "", "org_id": "", "created": "", "updated": "", "source": "afrinic", "raw": "mntner:         GENERATED-SHHIZMMOB7U3E6GZAMR0MCO1TGYE4UPU-MNT\\ndescr:          Auto-generated maintainer\\nadmin-c:        AGMT2310-AFRINIC\\nupd-to:         ***@afrinic.net\\nauth:           BCRYPT-PW # Filtered\\nmnt-by:         AFRINIC-HM-MNT\\nchanged:        ***@afrinic.net\\nsource:         AFRINIC\\n"}
{"id": "MAINT-AUCTORIZIUM-SG", "name": "Auctorizium Pte Ltd", "admin_id": "APLN3-AP", "tech_id": "", "org_id": "", "created": "", "updated": "2012-11-07", "source": "apnic", "raw": "mntner:         MAINT-AUCTORIZIUM-SG\\ndescr:          Auctorizium Pte Ltd\\ncountry:        SG\\nadmin-c:        APLN3-AP\\nupd-to:         R.Rajeshkumar@auctorizium.com\\nauth:           # Filtered\\nmnt-by:         MAINT-AUCTORIZIUM-SG\\nreferral-by:    APNIC-HM\\nlast-modified:  2012-11-07T05:54:59Z\\nsource:         APNIC"}
{"id": "POYRAZ-MNT", "name": "", "admin_id": "YEA14-RIPE", "tech_id": "", "org_id": "", "created": "2021-01-30", "updated": "2021-10-28", "source": "ripe", "raw": "mntner:         POYRAZ-MNT\\nadmin-c:        YEA14-RIPE\\nupd-to:         info@poyrazhosting.com.tr\\nauth:           SSO\\nmnt-by:         POYRAZ-MNT\\ncreated:        2021-01-30T18:18:00Z\\nlast-modified:  2021-10-28T01:08:43Z\\nsource:         RIPE"}
{"id": "MAINT-IN-GULBARGAMEGASPEED", "name": "GULBARGA MEGA SPEED PRIVATE LIMITED", "admin_id": "IM650-AP", "tech_id": "", "org_id": "", "created": "", "updated": "2017-09-30", "source": "apnic", "raw": "mntner:         MAINT-IN-GULBARGAMEGASPEED\\ndescr:          GULBARGA MEGA SPEED PRIVATE LIMITED\\nadmin-c:        IM650-AP\\nupd-to:         syedmuhammad.alihussain@yahoo.com\\nmnt-by:         MAINT-IN-GULBARGAMEGASPEED\\nauth:           # Filtered\\nreferral-by:    APNIC-HM\\nlast-modified:  2017-09-30T09:04:46Z\\nsource:         APNIC"}
{"id": "GENERATED-XD5RYSQBQCNOFWJ3LCDQFYUX1OOQK2JD-MNT", "name": "Auto-generated maintainer", "admin_id": "AGMT2310-AFRINIC", "tech_id": "", "org_id": "", "created": "", "updated": "", "source": "afrinic", "raw": "mntner:         GENERATED-XD5RYSQBQCNOFWJ3LCDQFYUX1OOQK2JD-MNT\\ndescr:          Auto-generated maintainer\\nadmin-c:        AGMT2310-AFRINIC\\nauth:           BCRYPT-PW # Filtered\\nmnt-by:         AFRINIC-HM-MNT\\nupd-to:         ***@afrinic.net\\nchanged:        ***@afrinic.net\\nsource:         AFRINIC\\n"}
{"id": "MNT-SARNICA", "name": "Sarnica Ltd.", "admin_id": "AHB18-RIPE", "tech_id": "", "org_id": "", "created": "2008-12-04", "updated": "2018-01-22", "source": "ripe", "raw": "mntner:         MNT-SARNICA\\ndescr:          Sarnica Ltd.\\nadmin-c:        AHB18-RIPE\\nupd-to:         nebi78@abv.bg\\nauth:           SSO\\nremarks:        MD5 passwords older than November 2011 were removed from this maintainer, see: https://www.ripe.net/removed2011pw\\nmnt-by:         MNT-SARNICA\\ncreated:        2008-12-04T07:58:54Z\\nlast-modified:  2018-01-22T12:06:25Z\\nsource:         RIPE"}
{"id": "IBI-MNT", "name": "KRYON MANAGEMENT SRL\\nLOGOFAT LUCA STROICI 40\\nSECTOR 2\\nBUCHAREST, ROMANIA", "admin_id": "BV826-RIPE", "tech_id": "", "org_id": "", "created": "2005-07-11", "updated": "2025-06-25", "source": "ripe", "raw": "mntner:         IBI-MNT\\ndescr:          KRYON MANAGEMENT SRL\\ndescr:          LOGOFAT LUCA STROICI 40\\ndescr:          SECTOR 2\\ndescr:          BUCHAREST, ROMANIA\\nadmin-c:        BV826-RIPE\\nupd-to:         viziteu@gmail.com\\nauth:           SSO\\nmnt-by:         IBI-MNT\\nnotify:         viziteu@gmail.com\\ncreated:        2005-07-11T11:11:09Z\\nlast-modified:  2025-06-25T10:41:01Z\\nsource:         RIPE"}
{"id": "MAINT-JP-APPLIJP043", "name": "Appli Co,.Ltd", "admin_id": "TK569-AP", "tech_id": "", "org_id": "", "created": "", "updated": "2014-04-26", "source": "apnic", "raw": "mntner:         MAINT-JP-APPLIJP043\\ndescr:          Appli Co,.Ltd\\ncountry:        JP\\nadmin-c:        TK569-AP\\nupd-to:         support@appli-jp.com\\nauth:           # Filtered\\nmnt-by:         MAINT-JP-APPLIJP043\\nreferral-by:    APNIC-HM\\nlast-modified:  2014-04-26T22:11:04Z\\nsource:         APNIC"}
{"id": "APPNOR-MNT", "name": "Legacy MNT for APPNOR MSP\\nAppnor MSP SA\\nPromoroaca nr. 5 Et. 2 Camera 1\\n014013 Bucharest, Romania", "admin_id": "CHRT", "tech_id": "CHRT", "org_id": "", "created": "2011-01-21", "updated": "2020-10-20", "source": "ripe", "raw": "mntner:         APPNOR-MNT\\ndescr:          Legacy MNT for APPNOR MSP\\ndescr:          Appnor MSP SA\\ndescr:          Promoroaca nr. 5 Et. 2 Camera 1\\ndescr:          014013 Bucharest, Romania\\nadmin-c:        CHRT\\ntech-c:         CHRT\\nupd-to:         noc@chroot.ro\\nmnt-nfy:        noc@chroot.ro\\nauth:           SSO\\nauth:           SSO\\nnotify:         noc@chroot.ro\\nmnt-by:         APPNOR-MNT\\nmnt-by:         CHROOT-MNT\\ncreated:        2011-01-21T08:36:24Z\\nlast-modified:  2020-10-20T18:44:14Z\\nsource:         RIPE"}
{"id": "INTELLECOM-MNT", "name": "Intellecom mantainer\\ntest", "admin_id": "INCC2-RIPE", "tech_id": "INCC2-RIPE", "org_id": "ORG-IA60-RIPE", "created": "2009-10-19", "updated": "2018-09-14", "source": "ripe", "raw": "mntner:         INTELLECOM-MNT\\ndescr:          Intellecom mantainer\\norg:            ORG-IA60-RIPE\\nadmin-c:        INCC2-RIPE\\ntech-c:         INCC2-RIPE\\nupd-to:         ripe@intellecom.net.ua\\nmnt-nfy:        ripe@intellecom.net.ua\\nremarks:        MD5 passwords older than November 2011 were removed from this maintainer, see: https://www.ripe.net/removed2011pw\\nremarks:        Serge Podgorny\\nauth:           X509-3115\\nauth:           SSO\\nremarks:        Andrey Morozov\\nmnt-by:         INTELLECOM-MNT\\ncreated:        2009-10-19T11:26:29Z\\nlast-modified:  2018-09-14T13:14:52Z\\nsource:         RIPE\\ndescr:          test"}
{"id": "CY-CSPSCARTA-2-MNT", "name": "Startup maintainer", "admin_id": "GS17895-RIPE", "tech_id": "", "org_id": "", "created": "2016-01-14", "updated": "2016-01-14", "source": "ripe", "raw": "mntner:         cy-cspscarta-2-mnt\\ndescr:          Startup maintainer\\nadmin-c:        GS17895-RIPE\\nupd-to:         gsmith@cartaworldwide.com\\nauth:           SSO\\nmnt-by:         cy-cspscarta-2-mnt\\ncreated:        2016-01-14T13:12:19Z\\nlast-modified:  2016-01-14T14:33:11Z\\nsource:         RIPE"}
{"id": "VIYE-MNT", "name": "", "admin_id": "VIYE1", "tech_id": "", "org_id": "", "created": "2024-08-13", "updated": "2024-08-13", "source": "ripe", "raw": "mntner:         VIYE-MNT\\nadmin-c:        VIYE1\\nupd-to:         vitally@vitally.cv.ua\\nauth:           SSO\\nmnt-by:         VIYE-MNT\\ncreated:        2024-08-13T11:00:32Z\\nlast-modified:  2024-08-13T11:00:32Z\\nsource:         RIPE"}
{"id": "MAINT-ID-CLICKNET", "name": "PT. Mitra Global Multimedia\\nFatmawati Mas Business Center III/314\\nJl. Fatmawati no. 20\\nJakarta 12430\\nIndonesia", "admin_id": "RJ62-AP", "tech_id": "RJ62-AP", "org_id": "", "created": "", "updated": "2016-10-20", "source": "apnic", "raw": "mntner:         MAINT-ID-CLICKNET\\ndescr:          PT. Mitra Global Multimedia\\ndescr:          Fatmawati Mas Business Center III/314\\ndescr:          Jl. Fatmawati no. 20\\ndescr:          Jakarta 12430\\ndescr:          Indonesia\\ncountry:        ID\\nadmin-c:        RJ62-AP\\ntech-c:         RJ62-AP\\nupd-to:         riko@click.net.id\\nauth:           # Filtered\\nmnt-nfy:        riko@click.net.id\\nmnt-by:         MAINT-ID-CLICKNET\\nreferral-by:    APNIC-HM\\nlast-modified:  2016-10-20T00:52:43Z\\nsource:         APNIC"}
{"id": "GENERATED-PUGSF4ASC89WTL6ZPVMEBQ9CADJZXJP7-MNT", "name": "Auto-generated maintainer", "admin_id": "AGMT2310-AFRINIC", "tech_id": "", "org_id": "", "created": "", "updated": "", "source": "afrinic", "raw": "mntner:         GENERATED-PUGSF4ASC89WTL6ZPVMEBQ9CADJZXJP7-MNT\\ndescr:          Auto-generated maintainer\\nadmin-c:        AGMT2310-AFRINIC\\nupd-to:         hostmaster@afrinic.net\\nauth:           BCRYPT-PW # Filtered\\nmnt-by:         AFRINIC-HM-MNT\\nchanged:        hostmaster@afrinic.net\\nsource:         AFRINIC # Filtered"}
{"id": "GENERATED-MUWRZHX6H1K01XHJCRL34LASGV2N85W8-MNT", "name": "Auto-generated maintainer", "admin_id": "AGMT2310-AFRINIC", "tech_id": "", "org_id": "", "created": "", "updated": "", "source": "afrinic", "raw": "mntner:         GENERATED-MUWRZHX6H1K01XHJCRL34LASGV2N85W8-MNT\\ndescr:          Auto-generated maintainer\\nadmin-c:        AGMT2310-AFRINIC\\nupd-to:         ***@afrinic.net\\nauth:           BCRYPT-PW # Filtered\\nmnt-by:         AFRINIC-HM-MNT\\nchanged:        ***@afrinic.net\\nsource:         AFRINIC\\n"}
{"id": "NL-XRCSERVICES-1-MNT", "name": "Startup maintainer", "admin_id": "MS40192-RIPE", "tech_id": "ER5295-RIPE", "org_id": "", "created": "2016-03-15", "updated": "2016-03-15", "source": "ripe", "raw": "mntner:         nl-xrcservices-1-mnt\\ndescr:          Startup maintainer\\nadmin-c:        MS40192-RIPE\\ntech-c:         ER5295-RIPE\\nupd-to:         e.ruiten@xrc.nl\\nauth:           SSO\\nmnt-by:         nl-xrcservices-1-mnt\\ncreated:        2016-03-15T08:49:39Z\\nlast-modified:  2016-03-15T08:49:39Z\\nsource:         RIPE"}
{"id": "MAINT-MCT-PH", "name": "Mambulao Cable Television", "admin_id": "MCTA1-AP", "tech_id": "", "org_id": "", "created": "", "updated": "2021-07-19", "source": "apnic", "raw": "mntner:         MAINT-MCT-PH\\ndescr:          Mambulao Cable Television\\ncountry:        PH\\nadmin-c:        MCTA1-AP\\nupd-to:         mambulao_catv@yahoo.com\\nauth:           # Filtered\\nmnt-by:         MAINT-MCT-PH\\nreferral-by:    APNIC-HM\\nlast-modified:  2021-07-19T10:30:54Z\\nsource:         APNIC"}
{"id": "GENERATED-K0MQLXVNBRMIV1MUJZ2XPALVZCDCU0YR-MNT", "name": "Auto-generated maintainer", "admin_id": "AGMT2310-AFRINIC", "tech_id": "", "org_id": "", "created": "", "updated": "", "source": "afrinic", "raw": "mntner:         GENERATED-K0MQLXVNBRMIV1MUJZ2XPALVZCDCU0YR-MNT\\ndescr:          Auto-generated maintainer\\nadmin-c:        AGMT2310-AFRINIC\\nupd-to:         ***@afrinic.net\\nauth:           BCRYPT-PW # Filtered\\nmnt-by:         AFRINIC-HM-MNT\\nchanged:        ***@afrinic.net\\nsource:         AFRINIC\\n"}
{"id": "KYNM", "name": "", "admin_id": "NTH10-RIPE", "tech_id": "", "org_id": "", "created": "2016-12-23", "updated": "2016-12-23", "source": "ripe", "raw": "mntner:         kynm\\nadmin-c:        NTH10-RIPE\\nupd-to:         haunt1@viettel.com.vn\\nauth:           SSO\\nmnt-by:         kynm\\ncreated:        2016-12-23T06:27:23Z\\nlast-modified:  2016-12-23T06:27:23Z\\nsource:         RIPE"}
{"id": "MAINT-MYREPUBLIC-SG", "name": "MyRepublic Pte. Ltd.", "admin_id": "MNA17-AP", "tech_id": "", "org_id": "", "created": "", "updated": "2012-02-21", "source": "apnic", "raw": "mntner:         MAINT-MYREPUBLIC-SG\\ndescr:          MyRepublic Pte. Ltd.\\ncountry:        SG\\nadmin-c:        MNA17-AP\\nupd-to:         admin@myrepublic.com.sg\\nauth:           # Filtered\\nmnt-by:         MAINT-MYREPUBLIC-SG\\nreferral-by:    APNIC-HM\\nlast-modified:  2012-02-21T03:19:37Z\\nsource:         APNIC"}
{"id": "ICONA-MNT", "name": "ICONA for IT and Telecom. LTD Co", "admin_id": "SA72-AFRINIC", "tech_id": "TS50-AFRINIC\\nMA205-AFRINIC", "org_id": "", "created": "", "updated": "2024-11-11", "source": "afrinic", "raw": "mntner:         ICONA-mnt\\ndescr:          ICONA for IT and Telecom. LTD Co\\nadmin-c:        SA72-AFRINIC\\ntech-c:         TS50-AFRINIC\\ntech-c:         MA205-AFRINIC\\nupd-to:         s.boshala@icona.ly\\nmnt-nfy:        s.boshala@icona.ly\\nupd-to:         mohamed.awinat@icona.ly\\nmnt-nfy:        mohamed.awinat@icona.ly\\nauth:           BCRYPT-PW # Filtered\\nnotify:         hussain@icona.ly\\nmnt-by:         ICONA-mnt\\nchanged:        hiba@afrinic.net 20130219\\nchanged:        hostmaster@afrinic.net 20180724\\nchanged:        hostmaster@afrinic.net 20190322\\nchanged:        hostmaster@afrinic.net 20200420\\nchanged:        hostmaster@afrinic.net 20241111\\nsource:         AFRINIC # Filtered"}
{"id": "MAINT-ALOYSIUS-AU", "name": "ST ALOYSIUS COLLEGE", "admin_id": "TOTJ1-AP", "tech_id": "TOTJ1-AP", "org_id": "", "created": "", "updated": "2015-04-17", "source": "apnic", "raw": "mntner:         MAINT-ALOYSIUS-AU\\ndescr:          ST ALOYSIUS COLLEGE\\ncountry:        AU\\nadmin-c:        TOTJ1-AP\\ntech-c:         TOTJ1-AP\\nupd-to:         abuse@staloysius.nsw.edu.au\\nauth:           # Filtered\\nmnt-by:         MAINT-ALOYSIUS-AU\\nreferral-by:    APNIC-HM\\nlast-modified:  2015-04-17T05:38:10Z\\nsource:         APNIC"}
{"id": "MAINT-AP-HAYABUSA", "name": "hayabusa", "admin_id": "NM477-AP", "tech_id": "", "org_id": "", "created": "", "updated": "2013-06-13", "source": "apnic", "raw": "mntner:         MAINT-AP-HAYABUSA\\ndescr:          hayabusa\\nadmin-c:        NM477-AP\\nupd-to:         info@hayabusa.ne.jp\\nauth:           # Filtered\\nmnt-by:         MAINT-AP-HAYABUSA\\nreferral-by:    APNIC-HM\\nlast-modified:  2013-06-13T13:51:51Z\\nsource:         APNIC"}
{"id": "CZ-IPNODE-1-MNT", "name": "Startup maintainer", "admin_id": "TP6311-RIPE", "tech_id": "TP6311-RIPE", "org_id": "", "created": "2018-07-03", "updated": "2018-07-03", "source": "ripe", "raw": "mntner:         cz-ipnode-1-mnt\\ndescr:          Startup maintainer\\nadmin-c:        TP6311-RIPE\\ntech-c:         TP6311-RIPE\\nupd-to:         tpoder@ipnode.cz\\nauth:           SSO\\nauth:           SSO\\nauth:           SSO\\nmnt-by:         cz-ipnode-1-mnt\\ncreated:        2018-07-03T08:03:26Z\\nlast-modified:  2018-07-03T08:03:26Z\\nsource:         RIPE"}
{"id": "REDBEE-MNT", "name": "Red Bee Media", "admin_id": "LM5384-RIPE", "tech_id": "LM5384-RIPE", "org_id": "", "created": "2006-09-12", "updated": "2006-09-12", "source": "ripe", "raw": "mntner:         REDBEE-MNT\\ndescr:          Red Bee Media\\nadmin-c:        LM5384-RIPE\\ntech-c:         LM5384-RIPE\\nupd-to:         Lynsey.Mcdonnell@mxcplc.com\\nremarks:        MD5 passwords older than November 2011 were removed from this maintainer, see: https://www.ripe.net/removed2011pw\\nmnt-by:         REDBEE-MNT\\ncreated:        2006-09-12T09:08:46Z\\nlast-modified:  2006-09-12T09:08:46Z\\nsource:         RIPE"}
{"id": "MAINT-IN-MCVPL", "name": "MALAYALAM CABLE VISION PRIVATE LIMITED", "admin_id": "NM1941-AP", "tech_id": "", "org_id": "", "created": "", "updated": "2023-04-13", "source": "apnic", "raw": "mntner:         MAINT-IN-MCVPL\\ndescr:          MALAYALAM CABLE VISION PRIVATE LIMITED\\nadmin-c:        NM1941-AP\\nupd-to:         malayalamcablevision@gmail.com\\nmnt-by:         MAINT-IN-MCVPL\\nauth:           # Filtered\\nlast-modified:  2023-04-13T07:27:57Z\\nsource:         APNIC"}
{"id": "DENIC-24-TK3420", "name": "Startup maintainer", "admin_id": "TK6139-RIPE", "tech_id": "", "org_id": "", "created": "2014-09-04", "updated": "2025-06-25", "source": "ripe", "raw": "mntner:         DENIC-24-TK3420\\ndescr:          Startup maintainer\\nadmin-c:        TK6139-RIPE\\nupd-to:         t.krueger@barolagerhaus.de\\nauth:           SSO\\nauth:           SSO\\nmnt-by:         DENIC-24-TK3420\\ncreated:        2014-09-04T11:23:29Z\\nlast-modified:  2025-06-25T10:37:16Z\\nsource:         RIPE"}
{"id": "DE-BAYLFST-1-MNT", "name": "Bayerisches Landesamt fuer Steuern", "admin_id": "MH17333-RIPE\\nBR4034-RIPE\\nMT17943-RIPE\\nMH18903-RIPE", "tech_id": "BR4034-RIPE\\nMH17333-RIPE\\nMT17943-RIPE\\nMH18903-RIPE", "org_id": "", "created": "2016-11-04", "updated": "2025-06-12", "source": "ripe", "raw": "mntner:         de-baylfst-1-mnt\\ndescr:          Bayerisches Landesamt fuer Steuern\\nadmin-c:        MH17333-RIPE\\nadmin-c:        BR4034-RIPE\\nadmin-c:        MT17943-RIPE\\nadmin-c:        MH18903-RIPE\\ntech-c:         BR4034-RIPE\\ntech-c:         MH17333-RIPE\\ntech-c:         MT17943-RIPE\\ntech-c:         MH18903-RIPE\\nupd-to:         sublir@elster.de\\nmnt-nfy:        sublir@elster.de\\nauth:           SSO\\nauth:           SSO\\nauth:           SSO\\nauth:           SSO\\nauth:           SSO\\nmnt-by:         de-baylfst-1-mnt\\ncreated:        2016-11-04T09:37:14Z\\nlast-modified:  2025-06-12T16:30:23Z\\nsource:         RIPE"}
{"id": "GENERATED-XX1NH2SPILN3QPEB0ZJR76EMM6SOYHPK-MNT", "name": "Auto-generated maintainer", "admin_id": "AGMT2310-AFRINIC", "tech_id": "", "org_id": "", "created": "", "updated": "", "source": "afrinic", "raw": "mntner:         GENERATED-XX1NH2SPILN3QPEB0ZJR76EMM6SOYHPK-MNT\\ndescr:          Auto-generated maintainer\\nadmin-c:        AGMT2310-AFRINIC\\nupd-to:         ***@afrinic.net\\nauth:           BCRYPT-PW # Filtered\\nmnt-by:         AFRINIC-HM-MNT\\nchanged:        ***@afrinic.net\\nsource:         AFRINIC\\n"}
{"id": "EDEN-MNT", "name": "", "admin_id": "EU805-RIPE", "tech_id": "", "org_id": "", "created": "2024-07-29", "updated": "2024-07-29", "source": "ripe", "raw": "mntner:         eden-mnt\\nadmin-c:        EU805-RIPE\\nupd-to:         eden@cutegirls.club\\nauth:           SSO\\nmnt-by:         eden-mnt\\ncreated:        2024-07-29T23:32:49Z\\nlast-modified:  2024-07-29T23:32:49Z\\nsource:         RIPE"}
{"id": "MAINT-IPLINKNETWORK36-BD", "name": "Jahirul Islam t/a IP Link network", "admin_id": "ILNA41-AP", "tech_id": "", "org_id": "", "created": "", "updated": "2017-10-14", "source": "apnic", "raw": "mntner:         MAINT-IPLINKNETWORK36-BD\\ndescr:          Jahirul Islam t/a IP Link network\\ncountry:        BD\\nadmin-c:        ILNA41-AP\\nupd-to:         ceo@ip-linkisp.net\\nauth:           # Filtered\\nmnt-by:         MAINT-IPLINKNETWORK36-BD\\nreferral-by:    APNIC-HM\\nlast-modified:  2017-10-14T13:30:45Z\\nsource:         APNIC"}
{"id": "KNAUF", "name": "Maintainer", "admin_id": "KGD4-RIPE", "tech_id": "", "org_id": "", "created": "2012-01-19", "updated": "2025-07-16", "source": "ripe", "raw": "mntner:         knauf\\ndescr:          Maintainer\\nadmin-c:        KGD4-RIPE\\nupd-to:         sergey.moot@knauf.ua\\nmnt-by:         knauf\\nnotify:         sergey.moot@knauf.ua\\nremarks:        Accepted the RIPE Database Terms and Conditions\\ncreated:        2012-01-19T09:13:13Z\\nlast-modified:  2025-07-16T11:54:20Z\\nsource:         RIPE"}
{"id": "LFNET-MNT", "name": "LF.net Maintainer Object", "admin_id": "NF1-RIPE", "tech_id": "LNH2-ORG", "org_id": "", "created": "1970-01-01", "updated": "2024-02-23", "source": "ripe", "raw": "mntner:         LFNET-MNT\\ndescr:          LF.net Maintainer Object\\nadmin-c:        NF1-RIPE\\ntech-c:         LNH2-ORG\\nupd-to:         hostmaster@LF.net\\nmnt-nfy:        hostmaster@LF.net\\nauth:           PGPKEY-EACAD30F\\nauth:           SSO\\nmnt-by:         LFNET-MNT\\ncreated:        1970-01-01T00:00:00Z\\nlast-modified:  2024-02-23T15:23:58Z\\nsource:         RIPE"}
{"id": "MAINT-IN-SPIRAL", "name": "SPIRAL TECH", "admin_id": "KC1523-AP", "tech_id": "", "org_id": "", "created": "", "updated": "2021-08-06", "source": "apnic", "raw": "mntner:         MAINT-IN-SPIRAL\\ndescr:          SPIRAL TECH\\nadmin-c:        KC1523-AP\\nupd-to:         support@spiraltech.co.in\\nmnt-by:         MAINT-IN-SPIRAL\\nauth:           # Filtered\\nlast-modified:  2021-08-06T12:43:02Z\\nsource:         APNIC"}
{"id": "NPAS-MNT", "name": "ABY Plastik A.S.\\nABY Plastik A.S.", "admin_id": "DOL22-RIPE", "tech_id": "DOL22-RIPE", "org_id": "", "created": "2007-08-10", "updated": "2022-10-03", "source": "ripe", "raw": "mntner:         NPAS-MNT\\ndescr:          ABY Plastik A.S.\\ndescr:          ABY Plastik A.S.\\nadmin-c:        DOL22-RIPE\\ntech-c:         DOL22-RIPE\\nupd-to:         suat.altintas@dogantelekom.com\\nauth:           SSO\\nremarks:        MD5 passwords older than November 2011 were removed from this maintainer, see: https://www.ripe.net/removed2011pw\\nmnt-by:         NPAS-MNT\\ncreated:        2007-08-10T10:36:59Z\\nlast-modified:  2022-10-03T16:16:45Z\\nsource:         RIPE"}
{"id": "MNTNER_NETCORITES", "name": "", "admin_id": "DUMY-RIPE", "tech_id": "", "org_id": "", "created": "2020-02-03", "updated": "2020-02-03", "source": "ripe", "raw": "mntner:         mntner_NetCorites\\nadmin-c:        DUMY-RIPE\\nupd-to:         unread@ripe.net\\nauth:           MD5-PW $1$SaltSalt$DummifiedMD5HashValue.   # Real value hidden for security\\nmnt-by:         mntner_NetCorites\\ncreated:        2020-02-03T16:54:57Z\\nlast-modified:  2020-02-03T16:54:57Z\\nsource:         RIPE\\nremarks:        ****************************\\nremarks:        * THIS OBJECT IS MODIFIED\\nremarks:        * Please note that all data that is generally regarded as personal\\nremarks:        * data has been removed from this object.\\nremarks:        * To view the original object, please query the RIPE Database at:\\nremarks:        * http://www.ripe.net/whois\\nremarks:        ****************************\\n"}
{"id": "SK-DATAFOX-1-MNT", "name": "Startup maintainer", "admin_id": "MV13298-RIPE", "tech_id": "MV13298-RIPE", "org_id": "", "created": "2017-12-11", "updated": "2017-12-11", "source": "ripe", "raw": "mntner:         sk-datafox-1-mnt\\ndescr:          Startup maintainer\\nadmin-c:        MV13298-RIPE\\ntech-c:         MV13298-RIPE\\nupd-to:         lir@datafox.sk\\nauth:           SSO\\nmnt-by:         sk-datafox-1-mnt\\ncreated:        2017-12-11T17:46:42Z\\nlast-modified:  2017-12-11T17:46:42Z\\nsource:         RIPE"}
{"id": "GENERATED-XXQUJ2DCYDIKPW8EFZIJ4421RR0038YS-MNT", "name": "Auto-generated maintainer", "admin_id": "AGMT2310-AFRINIC", "tech_id": "", "org_id": "", "created": "", "updated": "", "source": "afrinic", "raw": "mntner:         GENERATED-XXQUJ2DCYDIKPW8EFZIJ4421RR0038YS-MNT\\ndescr:          Auto-generated maintainer\\nadmin-c:        AGMT2310-AFRINIC\\nupd-to:         ***@afrinic.net\\nauth:           BCRYPT-PW # Filtered\\nmnt-by:         AFRINIC-HM-MNT\\nchanged:        ***@afrinic.net\\nsource:         AFRINIC\\n"}
{"id": "INTERSAT-MNT", "name": "INTERSAT AFRICA LTD", "admin_id": "WT8-afrinic", "tech_id": "", "org_id": "", "created": "", "updated": "2019-05-30", "source": "afrinic", "raw": "mntner:         INTERSAT-MNT\\ndescr:          INTERSAT AFRICA LTD\\nadmin-c:        WT8-afrinic\\nupd-to:         wilson.thuo@intersat.ae\\nauth:           BCRYPT-PW # Filtered\\nmnt-by:         INTERSAT-MNT\\nchanged:        wilson.thuo@intersat.ae 20141203\\nchanged:        hostmaster@afrinic.net 20190530\\nsource:         AFRINIC # Filtered"}
{"id": "MAINT-AU-RR54-AP", "name": "Synthesised maintainer for Rob Roder", "admin_id": "RR54-AP", "tech_id": "RR54-AP", "org_id": "", "created": "", "updated": "2016-10-20", "source": "apnic", "raw": "mntner:         MAINT-AU-RR54-AP\\ndescr:          Synthesised maintainer for Rob Roder\\ncountry:        AU\\nadmin-c:        RR54-AP\\ntech-c:         RR54-AP\\nupd-to:         no-email-aunic-transfer@apnic.net\\nauth:           # Filtered\\nmnt-nfy:        no-email-aunic-transfer@apnic.net\\nremarks:        This maintainer was created based on data from the AUNIC database.\\nremarks:        The initial authorisation for objects protected by this mntner\\nremarks:        (objects that mention this mntner in the mnt-by field) is\\nremarks:        given at http://www.apnic.net/db/aunic/authorisation.html .\\nremarks:        Nic-hdl RR54-AP is based on data for RR6-AU in AUNIC database.\\nnotify:         no-email-aunic-transfer@apnic.net\\nmnt-by:         MAINT-AU-RR54-AP\\nreferral-by:    APNIC-HM\\nlast-modified:  2016-10-20T00:45:04Z\\nsource:         APNIC"}
{"id": "FR-NETTEL-1-MNT", "name": "Startup maintainer", "admin_id": "BC6230-RIPE", "tech_id": "BC6230-RIPE", "org_id": "", "created": "2016-01-22", "updated": "2016-01-22", "source": "ripe", "raw": "mntner:         fr-nettel-1-mnt\\ndescr:          Startup maintainer\\nadmin-c:        BC6230-RIPE\\ntech-c:         BC6230-RIPE\\nupd-to:         bertrand.cazal@nettel.Fr\\nauth:           SSO\\nmnt-by:         fr-nettel-1-mnt\\ncreated:        2016-01-22T10:52:12Z\\nlast-modified:  2016-01-22T10:52:12Z\\nsource:         RIPE"}
{"id": "DPS89", "name": "", "admin_id": "DP14473-RIPE", "tech_id": "", "org_id": "", "created": "2018-06-05", "updated": "2025-06-25", "source": "ripe", "raw": "mntner:         DPS89\\nadmin-c:        DP14473-RIPE\\nupd-to:         dmtrpopkov@gmail.com\\nauth:           SSO\\nmnt-by:         DPS89\\ncreated:        2018-06-05T08:40:38Z\\nlast-modified:  2025-06-25T10:43:56Z\\nsource:         RIPE"}
{"id": "MAINT-NINEFOLD-COM-AU", "name": "Ninefold Pty Limited", "admin_id": "NPLN3-AP", "tech_id": "", "org_id": "", "created": "", "updated": "2012-03-21", "source": "apnic", "raw": "mntner:         MAINT-NINEFOLD-COM-AU\\ndescr:          Ninefold Pty Limited\\ncountry:        AU\\nadmin-c:        NPLN3-AP\\nupd-to:         ops@ninefold.com\\nauth:           # Filtered\\nmnt-by:         MAINT-NINEFOLD-COM-AU\\nreferral-by:    APNIC-HM\\nlast-modified:  2012-03-21T05:12:47Z\\nsource:         APNIC"}
{"id": "EUROSKYPARK-MNT", "name": "", "admin_id": "UL494-RIPE", "tech_id": "", "org_id": "", "created": "2020-01-10", "updated": "2020-01-10", "source": "ripe", "raw": "mntner:         EUROSKYPARK-MNT\\nadmin-c:        UL494-RIPE\\nupd-to:         uwe.lahni@euroskypark.com\\nauth:           SSO\\nauth:           SSO\\nauth:           SSO\\nmnt-by:         EUROSKYPARK-MNT\\ncreated:        2020-01-10T10:14:25Z\\nlast-modified:  2020-01-10T10:14:53Z\\nsource:         RIPE"}
{"id": "JOLO22-MNT", "name": "", "admin_id": "JLN62-RIPE", "tech_id": "", "org_id": "", "created": "2022-12-07", "updated": "2022-12-07", "source": "ripe", "raw": "mntner:         jolo22-mnt\\nadmin-c:        JLN62-RIPE\\nupd-to:         johnleonavarro@radiologist.net\\nauth:           SSO\\nmnt-by:         jolo22-mnt\\ncreated:        2022-12-07T13:05:22Z\\nlast-modified:  2022-12-07T13:05:23Z\\nsource:         RIPE"}
{"id": "MAINT-KI-TKL", "name": "Television Kiribati Limited\\nBetio\\nKiribati", "admin_id": "TK446-AP", "tech_id": "SM578-AP", "org_id": "", "created": "", "updated": "2008-09-04", "source": "apnic", "raw": "mntner:         MAINT-KI-TKL\\ndescr:          Television Kiribati Limited\\ndescr:          Betio\\ndescr:          Kiribati\\nadmin-c:        TK446-AP\\ntech-c:         SM578-AP\\ncountry:        KI\\nreferral-by:    APNIC-HM\\nupd-to:         csharman@pwrcom.com.au\\nauth:           # Filtered\\nmnt-by:         MAINT-KI-TKL\\nlast-modified:  2008-09-04T07:29:00Z\\nsource:         APNIC"}
{"id": "MIKE-MNT", "name": "Michael Butschek's Maintainer Object", "admin_id": "MB-RIPE", "tech_id": "", "org_id": "", "created": "2007-10-13", "updated": "2025-07-02", "source": "ripe", "raw": "mntner:         MIKE-MNT\\ndescr:          Michael Butschek's Maintainer Object\\nadmin-c:        MB-RIPE\\nupd-to:         ripe@butschek.de\\nnotify:         ripe@butschek.de\\nmnt-nfy:        ripe@butschek.de\\nauth:           SSO\\nmnt-by:         MIKE-MNT\\ncreated:        2007-10-13T02:01:21Z\\nlast-modified:  2025-07-02T13:09:57Z\\nsource:         RIPE"}
{"id": "BROKEN-MNT", "name": "", "admin_id": "AA37814-RIPE", "tech_id": "", "org_id": "", "created": "2021-07-18", "updated": "2021-07-18", "source": "ripe", "raw": "mntner:         BrokeN-MNT\\nadmin-c:        AA37814-RIPE\\nupd-to:         flandry@flinfo.ca\\nauth:           SSO\\nmnt-by:         BrokeN-MNT\\ncreated:        2021-07-18T23:55:46Z\\nlast-modified:  2021-07-18T23:55:46Z\\nsource:         RIPE"}
{"id": "GATUNO-MNT", "name": "", "admin_id": "GA13145-RIPE", "tech_id": "", "org_id": "", "created": "2024-03-29", "updated": "2024-03-29", "source": "ripe", "raw": "mntner:         GATUNO-MNT\\nadmin-c:        GA13145-RIPE\\nupd-to:         gatuno@gatuno.mx\\nauth:           SSO\\nmnt-by:         GATUNO-MNT\\ncreated:        2024-03-29T20:22:41Z\\nlast-modified:  2024-03-29T20:22:41Z\\nsource:         RIPE"}
{"id": "GENERATED-26X1O9XRYVPN75XQWE4RHY5BMBDLJIIH-MNT", "name": "Auto-generated maintainer", "admin_id": "AGMT2310-AFRINIC", "tech_id": "", "org_id": "", "created": "", "updated": "", "source": "afrinic", "raw": "mntner:         GENERATED-26X1O9XRYVPN75XQWE4RHY5BMBDLJIIH-MNT\\ndescr:          Auto-generated maintainer\\nadmin-c:        AGMT2310-AFRINIC\\nupd-to:         hostmaster@afrinic.net\\nauth:           BCRYPT-PW # Filtered\\nmnt-by:         AFRINIC-HM-MNT\\nchanged:        hostmaster@afrinic.net\\nsource:         AFRINIC # Filtered"}
{"id": "MAINT-TYRASUKI-BG", "name": "Jori Vanneste", "admin_id": "JV173-AP", "tech_id": "", "org_id": "", "created": "", "updated": "2019-07-20", "source": "apnic", "raw": "mntner:         MAINT-TYRASUKI-BG\\ndescr:          Jori Vanneste\\nadmin-c:        JV173-AP\\nupd-to:         tyrasuki@pm.me\\nauth:           # Filtered\\nmnt-by:         MAINT-SOONKEATNEO-SG\\nlast-modified:  2019-07-20T02:31:18Z\\nnotify:         noc@soonkeat.sg\\nsource:         APNIC\\n"}
{"id": "MNT-US-RABBITSPOWERX-1", "name": "Startup maintainer", "admin_id": "YY1094-RIPE", "tech_id": "YY1094-RIPE", "org_id": "", "created": "2019-04-10", "updated": "2019-04-10", "source": "ripe", "raw": "mntner:         mnt-us-rabbitspowerx-1\\ndescr:          Startup maintainer\\nadmin-c:        YY1094-RIPE\\ntech-c:         YY1094-RIPE\\nupd-to:         rabbitspowerllc@gmail.com\\nauth:           SSO\\nmnt-by:         mnt-us-rabbitspowerx-1\\ncreated:        2019-04-10T12:49:47Z\\nlast-modified:  2019-04-10T12:49:47Z\\nsource:         RIPE"}
{"id": "LIR-IR-AIDAAHMADI-1-MNT", "name": "Startup maintainer", "admin_id": "AA40320-RIPE", "tech_id": "AA40320-RIPE", "org_id": "", "created": "2023-01-02", "updated": "2025-03-11", "source": "ripe", "raw": "mntner:         lir-ir-aidaahmadi-1-MNT\\ndescr:          Startup maintainer\\nadmin-c:        AA40320-RIPE\\ntech-c:         AA40320-RIPE\\nupd-to:         aida.ahmady1364@gmail.com\\nauth:           SSO\\nauth:           SSO\\nauth:           SSO\\nauth:           SSO\\nmnt-by:         lir-ir-aidaahmadi-1-MNT\\ncreated:        2023-01-02T11:14:48Z\\nlast-modified:  2025-03-11T20:49:30Z\\nsource:         RIPE"}
{"id": "MAINT-LITTLEBOYSNET-BD", "name": "Little Boys. Net", "admin_id": "LBNA1-AP", "tech_id": "", "org_id": "", "created": "", "updated": "2020-02-20", "source": "apnic", "raw": "mntner:         MAINT-LITTLEBOYSNET-BD\\ndescr:          Little Boys. Net\\ncountry:        BD\\nadmin-c:        LBNA1-AP\\nupd-to:         noc@littleboys.com.bd\\nauth:           # Filtered\\nmnt-by:         MAINT-LITTLEBOYSNET-BD\\nreferral-by:    APNIC-HM\\nlast-modified:  2020-02-20T23:38:13Z\\nsource:         APNIC"}
{"id": "MAINT-ID-BADAKGS", "name": "PT. Badak Global Swatantra\\nJl. Raya Tanjung Lesung Km.2 Kp. Mekarjaya\\nPandeglang, Banten, 42281", "admin_id": "UM42-AP", "tech_id": "UM42-AP", "org_id": "", "created": "", "updated": "2023-06-23", "source": "idnic", "raw": "mntner:         MAINT-ID-BADAKGS\\ndescr:          PT. Badak Global Swatantra\\ndescr:          Jl. Raya Tanjung Lesung Km.2 Kp. Mekarjaya\\ndescr:          Pandeglang, Banten, 42281\\nadmin-c:        UM42-AP\\nupd-to:         uj.marjuki@badak-gs.com\\nmnt-by:         MAINT-ID-BADAKGS\\nauth:           # Filtered\\ntech-c:         UM42-AP\\nreferral-by:    MNT-APJII-ID\\nlast-modified:  2023-06-23T06:18:38Z\\nsource:         IDNIC\\n"}
{"id": "MAINT-JP-GINGERLUCKLIMITED", "name": "Ginger Luck Limited", "admin_id": "JC4398-AP", "tech_id": "", "org_id": "", "created": "", "updated": "2019-01-09", "source": "apnic", "raw": "mntner:         MAINT-JP-GINGERLUCKLIMITED\\ndescr:          Ginger Luck Limited\\nadmin-c:        JC4398-AP\\nupd-to:         info032@zoho.com\\nmnt-by:         MAINT-JP-GINGERLUCKLIMITED\\nauth:           # Filtered\\nlast-modified:  2019-01-09T02:30:00Z\\nsource:         APNIC"}
{"id": "MAINT-EL-JP", "name": "Elmedia Co.,Ltd.", "admin_id": "ECNA2-AP", "tech_id": "", "org_id": "", "created": "", "updated": "2011-09-08", "source": "apnic", "raw": "mntner:         MAINT-EL-JP\\ndescr:          Elmedia Co.,Ltd.\\ncountry:        JP\\nadmin-c:        ECNA2-AP\\nupd-to:         info@elmedia.jp\\nauth:           # Filtered\\nmnt-by:         MAINT-EL-JP\\nreferral-by:    APNIC-HM\\nlast-modified:  2011-09-08T10:02:43Z\\nsource:         APNIC"}
{"id": "MAINT-ID-NAEK", "name": "PT NAEK SINAR CEMERLANG\\nJl.Pulo Gebang Permai No.14,Rt.013,Rw.004\\nPulo Gebang,Cakung\\nJakarta Timur 13950", "admin_id": "RR916-AP", "tech_id": "RR916-AP", "org_id": "", "created": "", "updated": "2025-02-25", "source": "apnic", "raw": "mntner:         MAINT-ID-NAEK\\ndescr:          PT NAEK SINAR CEMERLANG\\ndescr:          Jl.Pulo Gebang Permai No.14,Rt.013,Rw.004\\ndescr:          Pulo Gebang,Cakung\\ndescr:          Jakarta Timur 13950\\nadmin-c:        RR916-AP\\nupd-to:         reymondrolas@nschoster.com\\nauth:           # Filtered\\nmnt-by:         MAINT-ID-NAEK\\ntech-c:         RR916-AP\\nlast-modified:  2025-02-25T02:53:15Z\\nsource:         APNIC"}
{"id": "APHEKZ-MNT", "name": "", "admin_id": "DK10159-RIPE", "tech_id": "", "org_id": "", "created": "2022-02-03", "updated": "2022-02-03", "source": "ripe", "raw": "mntner:         APHEKZ-MNT\\nadmin-c:        DK10159-RIPE\\nupd-to:         daniel.kroczynski@gmail.com\\nauth:           SSO\\nmnt-by:         APHEKZ-MNT\\ncreated:        2022-02-03T08:26:06Z\\nlast-modified:  2022-02-03T08:26:06Z\\nsource:         RIPE"}
{"id": "MAINT-ID-NETSENTRA", "name": "PT NET Sentra Cyberindo\\nJl. Rajawali Raya B No.179\\nJaka Sampurna, Bekasi\\nJawa Barat 17145", "admin_id": "RT506-AP", "tech_id": "RT506-AP", "org_id": "", "created": "", "updated": "2020-11-04", "source": "idnic", "raw": "mntner:         MAINT-ID-NETSENTRA\\ndescr:          PT NET Sentra Cyberindo\\ndescr:          Jl. Rajawali Raya B No.179\\ndescr:          Jaka Sampurna, Bekasi\\ndescr:          Jawa Barat 17145\\ncountry:        ID\\nadmin-c:        RT506-AP\\ntech-c:         RT506-AP\\nupd-to:         hostmaster@netsentra.com\\nmnt-by:         MAINT-ID-NETSENTRA\\nauth:           # Filtered\\nremarks:        Send Spam & abuse reports to support@netsentra.com\\nreferral-by:    MNT-APJII-ID\\nlast-modified:  2020-11-04T11:12:39Z\\nsource:         IDNIC\\n"}
{"id": "MNT-UKHOST", "name": "UKHOST4U", "admin_id": "PH8096-RIPE", "tech_id": "", "org_id": "", "created": "2008-07-21", "updated": "2017-11-12", "source": "ripe", "raw": "mntner:         MNT-UKHOST\\ndescr:          UKHOST4U\\nadmin-c:        PH8096-RIPE\\nupd-to:         paul@ukhost4u.com\\nauth:           SSO\\nremarks:        MD5 passwords older than November 2011 were removed from this maintainer, see: https://www.ripe.net/removed2011pw\\nremarks:        UKHost4u\\nmnt-by:         MNT-HOST4U\\ncreated:        2008-07-21T20:58:33Z\\nlast-modified:  2017-11-12T12:02:50Z\\nsource:         RIPE"}
{"id": "MNT-RFERLCZ1", "name": "", "admin_id": "RL11488-RIPE", "tech_id": "", "org_id": "", "created": "2016-06-09", "updated": "2024-11-20", "source": "ripe", "raw": "mntner:         MNT-RFERLCZ1\\nadmin-c:        RL11488-RIPE\\nupd-to:         ntw@rferl.org\\nauth:           SSO\\nauth:           SSO\\nmnt-by:         MNT-RFERLCZ1\\ncreated:        2016-06-09T10:55:24Z\\nlast-modified:  2024-11-20T15:07:15Z\\nsource:         RIPE"}
{"id": "GENERATED-HIAOUOTGL0LO9BVK48TO8KCW5LWBLSCS-MNT", "name": "Auto-generated maintainer", "admin_id": "AGMT2310-AFRINIC", "tech_id": "", "org_id": "", "created": "", "updated": "", "source": "afrinic", "raw": "mntner:         GENERATED-HIAOUOTGL0LO9BVK48TO8KCW5LWBLSCS-MNT\\ndescr:          Auto-generated maintainer\\nadmin-c:        AGMT2310-AFRINIC\\nupd-to:         ***@afrinic.net\\nauth:           BCRYPT-PW # Filtered\\nmnt-by:         AFRINIC-HM-MNT\\nchanged:        ***@afrinic.net\\nsource:         AFRINIC\\n"}
{"id": "MAINT-IN-SMARTLOG", "name": "Smart Logic It Solutions", "admin_id": "MA1451-AP", "tech_id": "", "org_id": "", "created": "", "updated": "2020-05-13", "source": "apnic", "raw": "mntner:         MAINT-IN-SMARTLOG\\ndescr:          Smart Logic It Solutions\\nadmin-c:        MA1451-AP\\nupd-to:         sr.itgzb@hotmail.com\\nauth:           # Filtered\\nmnt-by:         MAINT-IN-SMARTLOG\\nlast-modified:  2020-05-13T06:14:27Z\\nsource:         APNIC"}
{"id": "MNT-NSTAR", "name": "NORTHSTAR", "admin_id": "ST2316-RIPE", "tech_id": "", "org_id": "", "created": "2011-03-06", "updated": "2011-03-06", "source": "ripe", "raw": "mntner:         MNT-NSTAR\\ndescr:          NORTHSTAR\\nadmin-c:        ST2316-RIPE\\nupd-to:         binoy@northstar.bh\\nremarks:        MD5 passwords older than November 2011 were removed from this maintainer, see: https://www.ripe.net/removed2011pw\\nmnt-by:         MNT-NSTAR\\ncreated:        2011-03-06T13:41:56Z\\nlast-modified:  2011-03-06T13:41:56Z\\nsource:         RIPE"}
{"id": "MAINT-MY-GSBPLANNING", "name": "GITN Sdn. Bhd.", "admin_id": "MHH6-AP", "tech_id": "MRAR2-AP", "org_id": "", "created": "", "updated": "2013-09-20", "source": "apnic", "raw": "mntner:         MAINT-MY-GSBPLANNING\\nupd-to:         hafizul@gitn.com.my\\ndescr:          GITN Sdn. Bhd.\\nauth:           # Filtered\\nadmin-c:        MHH6-AP\\ntech-c:         MRAR2-AP\\ncountry:        MY\\nmnt-nfy:        planning@gitn.com.my\\nreferral-by:    APNIC-HM\\nmnt-by:         MAINT-MY-GSBPLANNING\\nlast-modified:  2013-09-20T16:00:45Z\\nsource:         APNIC"}
{"id": "MAINT-IN-PERFECTIT1", "name": "PERFECT IT SERVICE", "admin_id": "SM2340-AP", "tech_id": "", "org_id": "", "created": "", "updated": "2023-04-20", "source": "apnic", "raw": "mntner:         MAINT-IN-PERFECTIT1\\ndescr:          PERFECT IT SERVICE\\nadmin-c:        SM2340-AP\\nupd-to:         infoperfectitservice@gmail.com\\nmnt-by:         MAINT-IN-PERFECTIT1\\nauth:           # Filtered\\nlast-modified:  2023-04-20T12:21:53Z\\nsource:         APNIC"}
{"id": "GENERATED-8NBIB1JAMTK7X6FZEF2UZXKSOEAQ1CZC-MNT", "name": "Auto-generated maintainer", "admin_id": "AGMT2310-AFRINIC", "tech_id": "", "org_id": "", "created": "", "updated": "", "source": "afrinic", "raw": "mntner:         GENERATED-8NBIB1JAMTK7X6FZEF2UZXKSOEAQ1CZC-MNT\\ndescr:          Auto-generated maintainer\\nadmin-c:        AGMT2310-AFRINIC\\nupd-to:         ***@afrinic.net\\nauth:           BCRYPT-PW # Filtered\\nmnt-by:         AFRINIC-HM-MNT\\nchanged:        ***@afrinic.net\\nsource:         AFRINIC\\n"}
{"id": "GENERATED-WF8PQHQ4MPY8VMDDCMGZRSGVFSDG4MJI-MNT", "name": "Auto-generated maintainer", "admin_id": "AGMT2310-AFRINIC", "tech_id": "", "org_id": "", "created": "", "updated": "", "source": "afrinic", "raw": "mntner:         GENERATED-WF8PQHQ4MPY8VMDDCMGZRSGVFSDG4MJI-MNT\\ndescr:          Auto-generated maintainer\\nadmin-c:        AGMT2310-AFRINIC\\nupd-to:         hostmaster@afrinic.net\\nauth:           BCRYPT-PW # Filtered\\nmnt-by:         AFRINIC-HM-MNT\\nchanged:        hostmaster@afrinic.net\\nsource:         AFRINIC # Filtered"}
{"id": "MNT-UMAC-NON-MO", "name": "maintainer for UMAC and associated nic-hdl", "admin_id": "TP137-AP", "tech_id": "TP137-AP", "org_id": "", "created": "", "updated": "2020-01-21", "source": "apnic", "raw": "mntner:         MNT-UMAC-NON-MO\\ndescr:          maintainer for UMAC and associated nic-hdl\\nadmin-c:        TP137-AP\\ntech-c:         TP137-AP\\nnotify:         bdl@umac.mo\\nmnt-by:         MNT-UMAC-NON-MO\\nupd-to:         bdl@umac.mo\\nauth:           # Filtered\\nreferral-by:    APNIC-HM\\nremarks:        ----------\\nremarks:        synthesized from ARIN objects:\\nremarks:        during import of network 161.64.0.0 - 161.64.255.255\\nremarks:        ----------\\nlast-modified:  2020-01-21T06:36:13Z\\nsource:         APNIC"}
{"id": "PS11964-RIPE", "name": "", "admin_id": "PS11964-RIPE", "tech_id": "", "org_id": "", "created": "2016-05-18", "updated": "2016-05-18", "source": "ripe", "raw": "mntner:         PS11964-RIPE\\nadmin-c:        PS11964-RIPE\\nupd-to:         peter@straznet.se\\nauth:           SSO\\nmnt-by:         PS11964-RIPE\\ncreated:        2016-05-18T13:28:42Z\\nlast-modified:  2016-05-18T13:28:42Z\\nsource:         RIPE"}
{"id": "MNT-HU-ORBIT-1", "name": "Startup maintainer", "admin_id": "BB11702-RIPE", "tech_id": "BB11702-RIPE", "org_id": "", "created": "2019-04-16", "updated": "2019-04-16", "source": "ripe", "raw": "mntner:         mnt-hu-orbit-1\\ndescr:          Startup maintainer\\nadmin-c:        BB11702-RIPE\\ntech-c:         BB11702-RIPE\\nupd-to:         bodecsb@vivanet.hu\\nauth:           SSO\\nmnt-by:         mnt-hu-orbit-1\\ncreated:        2019-04-16T07:43:02Z\\nlast-modified:  2019-04-16T07:43:02Z\\nsource:         RIPE"}
{"id": "TR-VEGANETDC-1-MNT", "name": "Startup maintainer", "admin_id": "UT683-RIPE", "tech_id": "UT683-RIPE", "org_id": "", "created": "2018-06-26", "updated": "2018-06-26", "source": "ripe", "raw": "mntner:         tr-veganetdc-1-mnt\\ndescr:          Startup maintainer\\nadmin-c:        UT683-RIPE\\ntech-c:         UT683-RIPE\\nupd-to:         destek@veganet.com.tr\\nauth:           SSO\\nmnt-by:         tr-veganetdc-1-mnt\\ncreated:        2018-06-26T09:51:38Z\\nlast-modified:  2018-06-26T09:51:38Z\\nsource:         RIPE"}
{"id": "NCS-RIPE-MNT", "name": "NCS RIPE administrator dep.", "admin_id": "RS728-RIPE", "tech_id": "RS728-RIPE", "org_id": "", "created": "2002-06-04", "updated": "2007-11-29", "source": "ripe", "raw": "mntner:         NCS-RIPE-MNT\\ndescr:          NCS RIPE administrator dep.\\nadmin-c:        RS728-RIPE\\ntech-c:         RS728-RIPE\\nupd-to:         ripe@nc-spectrum.no\\nmnt-nfy:        ripe@nc-spectrum.no\\nremarks:        MD5 passwords older than November 2011 were removed from this maintainer, see: https://www.ripe.net/removed2011pw\\nnotify:         ripe@nc-spectrum.no\\nmnt-by:         NCS-RIPE-MNT\\ncreated:        2002-06-04T15:44:10Z\\nlast-modified:  2007-11-29T07:56:48Z\\nsource:         RIPE"}
{"id": "MAINT-EASYNETWORK-BD", "name": "Md Arafath Romel t/a Easynetwork", "admin_id": "ENA33-AP", "tech_id": "", "org_id": "", "created": "", "updated": "2024-02-04", "source": "apnic", "raw": "mntner:         MAINT-EASYNETWORK-BD\\ndescr:          Md Arafath Romel t/a Easynetwork\\ncountry:        BD\\nadmin-c:        ENA33-AP\\nupd-to:         abuse@easynetowrkbd.com\\nauth:           # Filtered\\nmnt-by:         MAINT-EASYNETWORK-BD\\nreferral-by:    APNIC-HM\\nlast-modified:  2024-02-04T14:12:00Z\\nsource:         APNIC"}
{"id": "ES-SOLCORIP-1-MNT", "name": "Startup maintainer", "admin_id": "JRP43-RIPE", "tech_id": "JRP43-RIPE", "org_id": "", "created": "2018-05-18", "updated": "2018-05-18", "source": "ripe", "raw": "mntner:         es-solcorip-1-mnt\\ndescr:          Startup maintainer\\nadmin-c:        JRP43-RIPE\\ntech-c:         JRP43-RIPE\\nupd-to:         ripe2@conectabalear.com\\nauth:           SSO\\nmnt-by:         es-solcorip-1-mnt\\ncreated:        2018-05-18T13:54:17Z\\nlast-modified:  2018-05-18T13:54:17Z\\nsource:         RIPE"}